Metadata-Version: 2.4
Name: agentichub
Version: 1.17.0
Summary: Pydantic-AI based Multi-Agent Framework with YAML-based Agents, Teams, Workflows & Extended ACP / AGUI integration
Keywords: 
Author: Philipp Temminghoff
Author-email: Philipp Temminghoff <philipptemminghoff@googlemail.com>
License-Expression: MIT
License-File: LICENSE
Classifier: Development Status :: 4 - Beta
Classifier: Framework :: Pydantic
Classifier: Framework :: Pydantic :: 2
Classifier: Intended Audience :: Developers
Classifier: Operating System :: OS Independent
Classifier: Programming Language :: Python :: 3
Classifier: Programming Language :: Python :: 3 :: Only
Classifier: Programming Language :: Python :: 3.12
Classifier: Programming Language :: Python :: 3.13
Classifier: Programming Language :: Python :: 3.14
Classifier: Topic :: Documentation
Classifier: Topic :: Internet
Classifier: Topic :: Scientific/Engineering :: Artificial Intelligence
Classifier: Topic :: Software Development
Classifier: Topic :: Utilities
Classifier: Typing :: Typed
Requires-Dist: anyenv[httpx]>=0.3.0
Requires-Dist: docler>=1.0.3
Requires-Dist: docstring-parser>=0.17.0
Requires-Dist: epregistry
Requires-Dist: evented>=1.0.5
Requires-Dist: exxec>=0.1.0
Requires-Dist: fastmcp>=2.12.4
Requires-Dist: fsspec
Requires-Dist: httpx
Requires-Dist: jinja2
Requires-Dist: jinjarope
Requires-Dist: llmling-models>=0.2.0
Requires-Dist: logfire
Requires-Dist: mcp>=1.2.0
Requires-Dist: platformdirs
Requires-Dist: promptantic>=0.4.5
Requires-Dist: psygnal>=0.11.1
Requires-Dist: pydantic>=2.10.0
Requires-Dist: pydantic-ai-slim>=1.0.0
Requires-Dist: python-dotenv>=1.0.1
Requires-Dist: rich
Requires-Dist: schemez[codegen]
Requires-Dist: searchly[all]>=2.0.1
Requires-Dist: slashed>=0.1.0
Requires-Dist: sqlalchemy[aiosqlite]
Requires-Dist: sqlmodel>=0.0.22
Requires-Dist: structlog>=25.5.0
Requires-Dist: tokonomics>=0.1.2
Requires-Dist: toprompt>=0.0.1
Requires-Dist: typer
Requires-Dist: upathtools>=0.1.0
Requires-Dist: yamling>=2.0.2
Requires-Dist: fasta2a ; extra == 'a2a'
Requires-Dist: starlette ; extra == 'a2a'
Requires-Dist: ag-ui-protocol>=0.1.10 ; extra == 'ag-ui'
Requires-Dist: braintrust ; extra == 'braintrust'
Requires-Dist: autoevals ; extra == 'braintrust'
Requires-Dist: claude-agent-sdk>=0.1.18 ; extra == 'claude'
Requires-Dist: clipman ; extra == 'clipboard'
Requires-Dist: rustworkx>=0.17.1 ; extra == 'coding'
Requires-Dist: grep-ast ; extra == 'coding'
Requires-Dist: ast-grep-py>=0.40.0 ; extra == 'coding'
Requires-Dist: tree-sitter>=0.25.2 ; extra == 'coding'
Requires-Dist: tree-sitter-python>=0.25.0 ; extra == 'coding'
Requires-Dist: tree-sitter-c>=0.24.1 ; extra == 'coding'
Requires-Dist: tree-sitter-javascript>=0.25.0 ; extra == 'coding'
Requires-Dist: tree-sitter>=0.25.2 ; extra == 'coding'
Requires-Dist: tree-sitter-typescript>=0.23.0 ; extra == 'coding'
Requires-Dist: tree-sitter-cpp>=0.23.0 ; extra == 'coding'
Requires-Dist: tree-sitter-rust>=0.23.0 ; extra == 'coding'
Requires-Dist: tree-sitter-go>=0.23.0 ; extra == 'coding'
Requires-Dist: tree-sitter-json>=0.24.0 ; extra == 'coding'
Requires-Dist: tree-sitter-yaml>=0.6.0 ; extra == 'coding'
Requires-Dist: composio ; extra == 'composio'
Requires-Dist: pydantic-ai-slim[openai,google,anthropic,mistral,retries]>=1.0.0 ; extra == 'default'
Requires-Dist: evented[all] ; extra == 'events'
Requires-Dist: fsspec[git] ; extra == 'git'
Requires-Dist: langfuse ; extra == 'langfuse'
Requires-Dist: markitdown ; python_full_version < '3.14' and extra == 'markitdown'
Requires-Dist: mcpx-py>=0.7.0 ; extra == 'mcp-run'
Requires-Dist: typeagent>=0.3.3 ; extra == 'memory'
Requires-Dist: apprise>=1.9.5 ; extra == 'notifications'
Requires-Dist: keyring>=25.6.0 ; extra == 'oauth'
Requires-Dist: promptlayer ; extra == 'promptlayer'
Requires-Dist: logfire[fastapi] ; extra == 'server'
Requires-Dist: fastapi ; extra == 'server'
Requires-Dist: uvicorn[standard] ; extra == 'server'
Requires-Dist: textual>=1.0.0 ; extra == 'textual'
Requires-Dist: tiktoken ; extra == 'tiktoken'
Requires-Dist: openai>=1.0.0 ; extra == 'tts'
Requires-Dist: sounddevice>=0.5.0 ; extra == 'tts'
Requires-Dist: numpy>=1.24.0 ; extra == 'tts'
Requires-Dist: edge-tts>=7.0.0 ; extra == 'tts-edge'
Requires-Dist: miniaudio>=1.60 ; extra == 'tts-edge'
Requires-Dist: sounddevice>=0.5.0 ; extra == 'tts-edge'
Requires-Python: >=3.13
Project-URL: Code coverage, https://app.codecov.io/gh/phil65/llmling-agent
Project-URL: Discussions, https://github.com/phil65/llmling-agent/discussions
Project-URL: Documentation, https://phil65.github.io/llmling-agent/
Project-URL: Issues, https://github.com/phil65/llmling-agent/issues
Project-URL: Source, https://github.com/phil65/llmling-agent
Provides-Extra: a2a
Provides-Extra: ag-ui
Provides-Extra: braintrust
Provides-Extra: claude
Provides-Extra: clipboard
Provides-Extra: coding
Provides-Extra: composio
Provides-Extra: default
Provides-Extra: events
Provides-Extra: git
Provides-Extra: langfuse
Provides-Extra: markitdown
Provides-Extra: mcp-run
Provides-Extra: memory
Provides-Extra: notifications
Provides-Extra: oauth
Provides-Extra: promptlayer
Provides-Extra: server
Provides-Extra: textual
Provides-Extra: tiktoken
Provides-Extra: tts
Provides-Extra: tts-edge
